{
  "id": "2818281",
  "name": "The PASS 图标库",
  "font_family": "iconfont",
  "css_prefix_text": "icon-",
  "description": "",
  "glyphs": [
    {
      "icon_id": "33154339",
      "name": "标记",
      "font_class": "biaoji",
      "unicode": "e67c",
      "unicode_decimal": 59004
    },
    {
      "icon_id": "33154340",
      "name": "价值",
      "font_class": "jiazhi",
      "unicode": "e67d",
      "unicode_decimal": 59005
    },
    {
      "icon_id": "33154341",
      "name": "详情",
      "font_class": "xiangqing",
      "unicode": "e67e",
      "unicode_decimal": 59006
    },
    {
      "icon_id": "33042190",
      "name": "减2-63",
      "font_class": "jian2-63",
      "unicode": "e67b",
      "unicode_decimal": 59003
    },
    {
      "icon_id": "32768790",
      "name": "CSV-44",
      "font_class": "CSV-44",
      "unicode": "e67a",
      "unicode_decimal": 59002
    },
    {
      "icon_id": "32692864",
      "name": "下载",
      "font_class": "xiazai",
      "unicode": "e678",
      "unicode_decimal": 59000
    },
    {
      "icon_id": "32692865",
      "name": "分享2",
      "font_class": "fenxiang2",
      "unicode": "e679",
      "unicode_decimal": 59001
    },
    {
      "icon_id": "32471841",
      "name": "xlsx",
      "font_class": "xlsx",
      "unicode": "e676",
      "unicode_decimal": 58998
    },
    {
      "icon_id": "32471842",
      "name": "json",
      "font_class": "json",
      "unicode": "e677",
      "unicode_decimal": 58999
    },
    {
      "icon_id": "32470813",
      "name": "相机",
      "font_class": "xiangji",
      "unicode": "e66a",
      "unicode_decimal": 58986
    },
    {
      "icon_id": "32161720",
      "name": "筛选-01",
      "font_class": "shaixuan-01",
      "unicode": "e675",
      "unicode_decimal": 58997
    },
    {
      "icon_id": "31834055",
      "name": "合作-26",
      "font_class": "hezuo-26",
      "unicode": "e673",
      "unicode_decimal": 58995
    },
    {
      "icon_id": "31834056",
      "name": "勾-28",
      "font_class": "gou-28",
      "unicode": "e674",
      "unicode_decimal": 58996
    },
    {
      "icon_id": "31820825",
      "name": "切换-36",
      "font_class": "qiehuan-36",
      "unicode": "e672",
      "unicode_decimal": 58994
    },
    {
      "icon_id": "31713690",
      "name": "Directory",
      "font_class": "Directory",
      "unicode": "e66e",
      "unicode_decimal": 58990
    },
    {
      "icon_id": "31713691",
      "name": "Creator DAO",
      "font_class": "a-CreatorDAO",
      "unicode": "e66f",
      "unicode_decimal": 58991
    },
    {
      "icon_id": "31713692",
      "name": "Wiki",
      "font_class": "Wiki",
      "unicode": "e670",
      "unicode_decimal": 58992
    },
    {
      "icon_id": "31713693",
      "name": "blog",
      "font_class": "blog",
      "unicode": "e671",
      "unicode_decimal": 58993
    },
    {
      "icon_id": "31689526",
      "name": "菜单-31",
      "font_class": "caidan-31",
      "unicode": "e66c",
      "unicode_decimal": 58988
    },
    {
      "icon_id": "31689817",
      "name": "转换-30",
      "font_class": "zhuanhuan-30",
      "unicode": "e66d",
      "unicode_decimal": 58989
    },
    {
      "icon_id": "31488339",
      "name": "复制2-29",
      "font_class": "fuzhi2-29",
      "unicode": "e66b",
      "unicode_decimal": 58987
    },
    {
      "icon_id": "31217774",
      "name": "排行榜-25",
      "font_class": "paihangbang-25",
      "unicode": "e669",
      "unicode_decimal": 58985
    },
    {
      "icon_id": "30996133",
      "name": "ETH2-24",
      "font_class": "ETH2-24",
      "unicode": "e668",
      "unicode_decimal": 58984
    },
    {
      "icon_id": "30822159",
      "name": "曲线图",
      "font_class": "Polygon-26",
      "unicode": "e667",
      "unicode_decimal": 58983
    },
    {
      "icon_id": "30726150",
      "name": "Ronin-25",
      "font_class": "Ronin-25",
      "unicode": "e665",
      "unicode_decimal": 58981
    },
    {
      "icon_id": "30726151",
      "name": "Polygon-24",
      "font_class": "Polygon-24",
      "unicode": "e666",
      "unicode_decimal": 58982
    },
    {
      "icon_id": "30722385",
      "name": "Etherscan-23",
      "font_class": "Etherscan-23",
      "unicode": "e664",
      "unicode_decimal": 58980
    },
    {
      "icon_id": "30386543",
      "name": "展开-20",
      "font_class": "zhankai-20",
      "unicode": "e658",
      "unicode_decimal": 58968
    },
    {
      "icon_id": "30386544",
      "name": "下跌-22",
      "font_class": "xiadie-22",
      "unicode": "e661",
      "unicode_decimal": 58977
    },
    {
      "icon_id": "30386545",
      "name": "上涨-21",
      "font_class": "shangzhang-21",
      "unicode": "e663",
      "unicode_decimal": 58979
    },
    {
      "icon_id": "28409846",
      "name": "opensea",
      "font_class": "opensea",
      "unicode": "e662",
      "unicode_decimal": 58978
    },
    {
      "icon_id": "29833514",
      "name": "代币-16",
      "font_class": "daibi-16",
      "unicode": "e660",
      "unicode_decimal": 58976
    },
    {
      "icon_id": "29608483",
      "name": "提示2-15",
      "font_class": "tishi2-15",
      "unicode": "e65f",
      "unicode_decimal": 58975
    },
    {
      "icon_id": "29607501",
      "name": "转换趋势图",
      "font_class": "zhuanhuanqushitu",
      "unicode": "e65d",
      "unicode_decimal": 58973
    },
    {
      "icon_id": "29607502",
      "name": "转换资产",
      "font_class": "zhuanhuanzichan",
      "unicode": "e65e",
      "unicode_decimal": 58974
    },
    {
      "icon_id": "29602472",
      "name": "Website-60",
      "font_class": "Website-60",
      "unicode": "e65c",
      "unicode_decimal": 58972
    },
    {
      "icon_id": "29602430",
      "name": "Foundation-62",
      "font_class": "Foundation-62",
      "unicode": "e659",
      "unicode_decimal": 58969
    },
    {
      "icon_id": "29575024",
      "name": "认证-12",
      "font_class": "renzheng-121",
      "unicode": "e65b",
      "unicode_decimal": 58971
    },
    {
      "icon_id": "29555524",
      "name": "link-61",
      "font_class": "link-61",
      "unicode": "e65a",
      "unicode_decimal": 58970
    },
    {
      "icon_id": "29554267",
      "name": "discrod",
      "font_class": "discrod2",
      "unicode": "e653",
      "unicode_decimal": 58963
    },
    {
      "icon_id": "29554268",
      "name": "Whitebook",
      "font_class": "Whitebook",
      "unicode": "e654",
      "unicode_decimal": 58964
    },
    {
      "icon_id": "29554269",
      "name": "icon-kfckfc",
      "font_class": "Twitter2",
      "unicode": "e655",
      "unicode_decimal": 58965
    },
    {
      "icon_id": "29554270",
      "name": "SR",
      "font_class": "SR",
      "unicode": "e656",
      "unicode_decimal": 58966
    },
    {
      "icon_id": "29554271",
      "name": "telegram",
      "font_class": "telegram",
      "unicode": "e657",
      "unicode_decimal": 58967
    },
    {
      "icon_id": "29530471",
      "name": "telegram-42",
      "font_class": "telegram-42",
      "unicode": "e652",
      "unicode_decimal": 58962
    },
    {
      "icon_id": "29529164",
      "name": "认证-12",
      "font_class": "renzheng-12",
      "unicode": "e651",
      "unicode_decimal": 58961
    },
    {
      "icon_id": "29384303",
      "name": "USDT",
      "font_class": "USDT",
      "unicode": "e64f",
      "unicode_decimal": 58959
    },
    {
      "icon_id": "29384304",
      "name": "ETH",
      "font_class": "ETH",
      "unicode": "e650",
      "unicode_decimal": 58960
    },
    {
      "icon_id": "29131150",
      "name": "钱包-07",
      "font_class": "qianbao-07",
      "unicode": "e64d",
      "unicode_decimal": 58957
    },
    {
      "icon_id": "29130954",
      "name": "sell-09",
      "font_class": "sell-09",
      "unicode": "e64e",
      "unicode_decimal": 58958
    },
    {
      "icon_id": "28990619",
      "name": "邮箱-06",
      "font_class": "youxiang-06",
      "unicode": "e64c",
      "unicode_decimal": 58956
    },
    {
      "icon_id": "28986422",
      "name": "discrod实色",
      "font_class": "discrodshise",
      "unicode": "e648",
      "unicode_decimal": 58952
    },
    {
      "icon_id": "28986423",
      "name": "葫芦",
      "font_class": "hulu",
      "unicode": "e649",
      "unicode_decimal": 58953
    },
    {
      "icon_id": "28986424",
      "name": "icon-kfckfc",
      "font_class": "twittershise",
      "unicode": "e64a",
      "unicode_decimal": 58954
    },
    {
      "icon_id": "28986425",
      "name": "telegram实色",
      "font_class": "telegramshise",
      "unicode": "e64b",
      "unicode_decimal": 58955
    },
    {
      "icon_id": "28941514",
      "name": "添加照片-01",
      "font_class": "tianjiazhaopian-01",
      "unicode": "e647",
      "unicode_decimal": 58951
    },
    {
      "icon_id": "28776490",
      "name": "加载-52",
      "font_class": "jiazai-52",
      "unicode": "e646",
      "unicode_decimal": 58950
    },
    {
      "icon_id": "28698467",
      "name": "错误文件-51",
      "font_class": "cuowuwenjian-51",
      "unicode": "e645",
      "unicode_decimal": 58949
    },
    {
      "icon_id": "28694896",
      "name": "xls-50",
      "font_class": "xls-50",
      "unicode": "e644",
      "unicode_decimal": 58948
    },
    {
      "icon_id": "28270060",
      "name": "头像",
      "font_class": "touxiang",
      "unicode": "e643",
      "unicode_decimal": 58947
    },
    {
      "icon_id": "28128878",
      "name": "批量操作-48",
      "font_class": "piliangcaozuo-48",
      "unicode": "e642",
      "unicode_decimal": 58946
    },
    {
      "icon_id": "28118856",
      "name": "时钟-47",
      "font_class": "shizhong-47",
      "unicode": "e641",
      "unicode_decimal": 58945
    },
    {
      "icon_id": "28107562",
      "name": "添加-46",
      "font_class": "tianjia-46",
      "unicode": "e640",
      "unicode_decimal": 58944
    },
    {
      "icon_id": "27993806",
      "name": "有限",
      "font_class": "youxian",
      "unicode": "e63f",
      "unicode_decimal": 58943
    },
    {
      "icon_id": "27980390",
      "name": "链接-44",
      "font_class": "lianjie-44",
      "unicode": "e63e",
      "unicode_decimal": 58942
    },
    {
      "icon_id": "27766389",
      "name": "discrod",
      "font_class": "discrod1",
      "unicode": "e63d",
      "unicode_decimal": 58941
    },
    {
      "icon_id": "27766359",
      "name": "discrod",
      "font_class": "discrod",
      "unicode": "e63b",
      "unicode_decimal": 58939
    },
    {
      "icon_id": "27766013",
      "name": "网址-43",
      "font_class": "wangzhi-43",
      "unicode": "e63c",
      "unicode_decimal": 58940
    },
    {
      "icon_id": "27750735",
      "name": "icon-kfckfc",
      "font_class": "Twitterlanse-40",
      "unicode": "e639",
      "unicode_decimal": 58937
    },
    {
      "icon_id": "27750521",
      "name": "icon-kfckfc",
      "font_class": "Twitter",
      "unicode": "e638",
      "unicode_decimal": 58936
    },
    {
      "icon_id": "27135889",
      "name": "减",
      "font_class": "jian",
      "unicode": "e636",
      "unicode_decimal": 58934
    },
    {
      "icon_id": "27135890",
      "name": "加",
      "font_class": "jia",
      "unicode": "e637",
      "unicode_decimal": 58935
    },
    {
      "icon_id": "27135410",
      "name": "点赞:hover",
      "font_class": "a-dianzanhover",
      "unicode": "e634",
      "unicode_decimal": 58932
    },
    {
      "icon_id": "27104738",
      "name": "勾",
      "font_class": "gou",
      "unicode": "e632",
      "unicode_decimal": 58930
    },
    {
      "icon_id": "27104477",
      "name": "查看方式:列表",
      "font_class": "a-chakanfangshiliebiao",
      "unicode": "e62c",
      "unicode_decimal": 58924
    },
    {
      "icon_id": "27104478",
      "name": "更多:.svg",
      "font_class": "a-gengduosvg",
      "unicode": "e62d",
      "unicode_decimal": 58925
    },
    {
      "icon_id": "27104479",
      "name": "下箭头",
      "font_class": "xiajiantou",
      "unicode": "e62e",
      "unicode_decimal": 58926
    },
    {
      "icon_id": "27104480",
      "name": "上",
      "font_class": "shang1",
      "unicode": "e62f",
      "unicode_decimal": 58927
    },
    {
      "icon_id": "27104481",
      "name": "无限",
      "font_class": "wuxian",
      "unicode": "e630",
      "unicode_decimal": 58928
    },
    {
      "icon_id": "27104482",
      "name": "下",
      "font_class": "xia1",
      "unicode": "e631",
      "unicode_decimal": 58929
    },
    {
      "icon_id": "27101195",
      "name": "创建",
      "font_class": "chuangjian",
      "unicode": "e629",
      "unicode_decimal": 58921
    },
    {
      "icon_id": "27101196",
      "name": "下",
      "font_class": "xia",
      "unicode": "e62a",
      "unicode_decimal": 58922
    },
    {
      "icon_id": "27101197",
      "name": "添加图片",
      "font_class": "tianjiatupian",
      "unicode": "e62b",
      "unicode_decimal": 58923
    },
    {
      "icon_id": "27101193",
      "name": "离开",
      "font_class": "likai",
      "unicode": "e627",
      "unicode_decimal": 58919
    },
    {
      "icon_id": "27101194",
      "name": "设置",
      "font_class": "shezhi",
      "unicode": "e628",
      "unicode_decimal": 58920
    },
    {
      "icon_id": "27101182",
      "name": "返回",
      "font_class": "fanhui",
      "unicode": "e61c",
      "unicode_decimal": 58908
    },
    {
      "icon_id": "27101183",
      "name": "编辑",
      "font_class": "bianji",
      "unicode": "e61d",
      "unicode_decimal": 58909
    },
    {
      "icon_id": "27101184",
      "name": "查看方式",
      "font_class": "chakanfangshi",
      "unicode": "e61e",
      "unicode_decimal": 58910
    },
    {
      "icon_id": "27101185",
      "name": "提示",
      "font_class": "tishi",
      "unicode": "e61f",
      "unicode_decimal": 58911
    },
    {
      "icon_id": "27101186",
      "name": "日历",
      "font_class": "rili",
      "unicode": "e620",
      "unicode_decimal": 58912
    },
    {
      "icon_id": "27101187",
      "name": "警告",
      "font_class": "jinggao",
      "unicode": "e621",
      "unicode_decimal": 58913
    },
    {
      "icon_id": "27101188",
      "name": "分享",
      "font_class": "fenxiang",
      "unicode": "e622",
      "unicode_decimal": 58914
    },
    {
      "icon_id": "27101189",
      "name": "解锁",
      "font_class": "jiesuo",
      "unicode": "e623",
      "unicode_decimal": 58915
    },
    {
      "icon_id": "27101190",
      "name": "房间",
      "font_class": "fangjian",
      "unicode": "e624",
      "unicode_decimal": 58916
    },
    {
      "icon_id": "27101191",
      "name": "上",
      "font_class": "shang",
      "unicode": "e625",
      "unicode_decimal": 58917
    },
    {
      "icon_id": "27097675",
      "name": "评论",
      "font_class": "pinglun",
      "unicode": "e61b",
      "unicode_decimal": 58907
    },
    {
      "icon_id": "27097666",
      "name": "更多",
      "font_class": "gengduo",
      "unicode": "e612",
      "unicode_decimal": 58898
    },
    {
      "icon_id": "27097667",
      "name": "发送",
      "font_class": "fasong",
      "unicode": "e613",
      "unicode_decimal": 58899
    },
    {
      "icon_id": "27097668",
      "name": "点赞",
      "font_class": "dianzan",
      "unicode": "e614",
      "unicode_decimal": 58900
    },
    {
      "icon_id": "27097669",
      "name": "进入",
      "font_class": "jinru",
      "unicode": "e615",
      "unicode_decimal": 58901
    },
    {
      "icon_id": "27097670",
      "name": "文档",
      "font_class": "wendang",
      "unicode": "e616",
      "unicode_decimal": 58902
    },
    {
      "icon_id": "27097671",
      "name": "添加文档",
      "font_class": "tianjiawendang",
      "unicode": "e617",
      "unicode_decimal": 58903
    },
    {
      "icon_id": "27097672",
      "name": "图片",
      "font_class": "tupian",
      "unicode": "e618",
      "unicode_decimal": 58904
    },
    {
      "icon_id": "27097673",
      "name": "井号",
      "font_class": "jinghao",
      "unicode": "e619",
      "unicode_decimal": 58905
    },
    {
      "icon_id": "27097674",
      "name": "表情",
      "font_class": "biaoqing",
      "unicode": "e61a",
      "unicode_decimal": 58906
    },
    {
      "icon_id": "27096197",
      "name": "锁定",
      "font_class": "suoding",
      "unicode": "e611",
      "unicode_decimal": 58897
    },
    {
      "icon_id": "27096125",
      "name": "left",
      "font_class": "left",
      "unicode": "e60d",
      "unicode_decimal": 58893
    },
    {
      "icon_id": "27096126",
      "name": "right",
      "font_class": "right",
      "unicode": "e60e",
      "unicode_decimal": 58894
    },
    {
      "icon_id": "27096127",
      "name": "置顶",
      "font_class": "zhiding",
      "unicode": "e60f",
      "unicode_decimal": 58895
    },
    {
      "icon_id": "27096128",
      "name": "关闭",
      "font_class": "guanbi",
      "unicode": "e610",
      "unicode_decimal": 58896
    },
    {
      "icon_id": "27095407",
      "name": "人数",
      "font_class": "renshu",
      "unicode": "e60a",
      "unicode_decimal": 58890
    },
    {
      "icon_id": "27095408",
      "name": "MIC",
      "font_class": "MIC",
      "unicode": "e60b",
      "unicode_decimal": 58891
    },
    {
      "icon_id": "27095409",
      "name": "浏览量",
      "font_class": "liulanliang",
      "unicode": "e60c",
      "unicode_decimal": 58892
    },
    {
      "icon_id": "27095280",
      "name": "搜索",
      "font_class": "sousuo1",
      "unicode": "e609",
      "unicode_decimal": 58889
    }
  ]
}
